eli_hello/__init__.py
eli_hello/app.py
eli_hello-0.0.1.dist-info/METADATA
eli_hello-0.0.1.dist-info/WHEEL
eli_hello-0.0.1.dist-info/RECORD
