Metadata-Version: 2.1
Name: eli-hello
Version: 0.0.1
Summary: 
Author: Eli Mayost
Author-email: eli.mayost@googlemail.com
Requires-Python: >=3.11,<4.0
Classifier: Programming Language :: Python :: 3
Classifier: Programming Language :: Python :: 3.11
Classifier: Programming Language :: Python :: 3.12
Requires-Dist: flask (>=3.0.3,<4.0.0)
Requires-Dist: gunicorn (>=22.0.0,<23.0.0)
Requires-Dist: poethepoet (>=0.26.1,<0.27.0)
